biblemateweb/README.md
biblemateweb/__init__.py
biblemateweb/config.py
biblemateweb/eliranwong.jpg
biblemateweb/main.py
biblemateweb/package_name.txt
biblemateweb/requirements.txt
biblemateweb/version.txt
biblemateweb/css/original.py
biblemateweb/fx/bible.py
biblemateweb/fx/original.py
biblemateweb/js/bible.py
biblemateweb/js/original.py
biblemateweb/js/sync_scrolling.py
biblemateweb/pages/README.md
biblemateweb/pages/home.py
biblemateweb/pages/ai/chat.py
biblemateweb/pages/bibles/original_discourse.py
biblemateweb/pages/bibles/original_interlinear.py
biblemateweb/pages/bibles/original_linguistic.py
biblemateweb/pages/bibles/original_parallel.py
biblemateweb/pages/bibles/original_reader.py
biblemateweb/pages/tools/audio.py
biblemateweb/pages/tools/chronology.py
biblemateweb-0.0.11.dist-info/METADATA
biblemateweb-0.0.11.dist-info/WHEEL
biblemateweb-0.0.11.dist-info/entry_points.txt
biblemateweb-0.0.11.dist-info/top_level.txt
biblemateweb-0.0.11.dist-info/RECORD
